[
  {
    "Rout No": "P1",
    "Vendor": "FT",
    "Emp ID": "Escort",
    "Name": "Escort",
    "Contact No": "Escort",
    "E mail ID": "Escort",
    "Address": "Escort",
    "Shift Time": "Escort",
    "Pick up point": "Escort",
    "Driver Details": "MH49CW0078",
    "M/F": "M",
    "Driver Address ": "S/O Pradip Krushnarao Wasnik, near gajanan maharaj mandir, 220, new balaji nagar vistar, \nmanewada road, bhgwan nagar, Nagpur, Maharashtra-440027"
  },
  {
    "Rout No": "P1",
    "Vendor": "FT",
    "Emp ID": "2571613",
    "Name": "Akansha Khode",
    "Contact No": "7773902239",
    "E mail ID": "akansha.khode@globallogic.com",
    "Address": "Plot No 22, Vijaya Nagar, opposite to VNIT main gate, \n south ambazari road, IT park Nagpur - 440022",
    "Shift Time": "05:00",
    "Pick up point": "Vijaya Nagar Main Gate",
    "Driver Details": "DRIVER-SURAJ",
    "M/F": "F",
    "Driver Address ": ""
  },
  {
    "Rout No": "P1",
    "Vendor": "FT",
    "Emp ID": "2524080",
    "Name": "Anshul Tyagi ",
    "Contact No": "7387683567",
    "E mail ID": "anshul.tyagi@globallogic.com",
    "Address": "Majestic Manor",
    "Shift Time": "",
    "Pick up point": "Majestic Manor",
    "Driver Details": "MOB-9561326459",
    "M/F": "",
    "Driver Address ": ""
  },
  {
    "Rout No": "P1",
    "Vendor": "FT",
    "Emp ID": "2573850",
    "Name": "Ritesh Kothawade",
    "Contact No": "9970609200",
    "E mail ID": "ritesh.kothawade@globallogic.com",
    "Address": "504, 7A, Mahindra Bloomdale, Mihan Sez, Khapri, Nagpur.",
    "Shift Time": "05:00",
    "Pick up point": "Bloomdale",
    "Driver Details": "",
    "M/F": "M",
    "Driver Address ": ""
  },
  {
    "Rout No": "P1",
    "Vendor": "FT",
    "Emp ID": "2575077",
    "Name": "Cheparthi Vasanthi",
    "Contact No": "7386270468",
    "E mail ID": "cheparthi.vasanthi@globallogic.com",
    "Address": "Moraj Apartments",
    "Shift Time": "05:00",
    "Pick up point": "Moraj Apartments",
    "Driver Details": "",
    "M/F": "F",
    "Driver Address ": ""
  },
  {
    "Rout No": "P1",
    "Vendor": "FT",
    "Emp ID": "NA",
    "Name": "Anima Dixit",
    "Contact No": "9717123008",
    "E mail ID": "anima.dixit@globallogic.com",
    "Address": "Shiv Kailasa, MIHAN, Nagpur, Sondapar",
    "Shift Time": "05:00",
    "Pick up point": "Shiv Kailasa",
    "Driver Details": "",
    "M/F": "F",
    "Driver Address ": ""
  },
  {
    "Rout No": "Rout No",
    "Vendor": "Vendor",
    "Emp ID": "Emp ID",
    "Name": "Name",
    "Contact No": "Contact No",
    "E mail ID": "E mail ID",
    "Address": "Address",
    "Shift Time": "Shift Time",
    "Pick up point": "Pick up point",
    "Driver Details": "Driver Details",
    "M/F": "M/F",
    "Driver Address ": ""
  },
  {
    "Rout No": "P2",
    "Vendor": "FT",
    "Emp ID": "2571735",
    "Name": "Mohammed Farshad Chenganakkattil",
    "Contact No": "9846412647",
    "E mail ID": "m.f.k@globallogic.com",
    "Address": "335, Nagar Vikas Housing Society, Narendra Nagar,Nagpur, Maharashtra-440015\"",
    "Shift Time": "05:00",
    "Pick up point": "Narendra Nagar",
    "Driver Details": "MH40CT4542",
    "M/F": "M",
    "Driver Address ": "House.No-285 Near Awachat Kirana Store Beldar Nagar, Narsala Hudkeshwar khurd. Nagpur (rural) Nagpur 440034"
  },
  {
    "Rout No": "P2",
    "Vendor": "FT",
    "Emp ID": "2575313",
    "Name": "B Prashanth",
    "Contact No": "8359938339",
    "E mail ID": "b.p.kumar2@globallogic.com",
    "Address": "Plot No. 57, Samaj Bhushan Society, Somalwada, Wardha Road,",
    "Shift Time": "05:00",
    "Pick up point": "Apollo Pharmacy",
    "Driver Details": "Driver-Tapan",
    "M/F": "M",
    "Driver Address ": ""
  },
  {
    "Rout No": "",
    "Vendor": "",
    "Emp ID": "",
    "Name": "",
    "Contact No": "",
    "E mail ID": "",
    "Address": "",
    "Shift Time": "",
    "Pick up point": "",
    "Driver Details": "Mob-8208223602",
    "M/F": "",
    "Driver Address ": ""
  },
  {
    "Rout No": "Rout No",
    "Vendor": "Vendor",
    "Emp ID": "Emp ID",
    "Name": "Name",
    "Contact No": "Contact No",
    "E mail ID": "E mail ID",
    "Address": "Address",
    "Shift Time": "Shift Time",
    "Pick up point": "Pick up point",
    "Driver Details": "Driver Details",
    "M/F": "M/F",
    "Driver Address ": ""
  },
  {
    "Rout No": "P3",
    "Vendor": "FT",
    "Emp ID": "2575102",
    "Name": "sohit mishra",
    "Contact No": "9096408407",
    "E mail ID": "sohit.mishra@globallogic.com",
    "Address": "Near Saiba towers Beside Sky Blue Farmhouse Gorewada Nagpur 441123",
    "Shift Time": "05:00",
    "Pick up point": "Saiba towers Gorewada",
    "Driver Details": "MH31FC8592",
    "M/F": "M",
    "Driver Address ": "91, SUDAM NAGARI, AMBAZARI, NAGPUR., NAGPUR (M CORP.) NAGPUR"
  },
  {
    "Rout No": "P3",
    "Vendor": "FT",
    "Emp ID": "NA",
    "Name": "Aniket Anand",
    "Contact No": "7089023911",
    "E mail ID": "",
    "Address": "B-403, Swapnil Enclave, Amravati Road, Kachimet, Nagpur - 440023",
    "Shift Time": "05:00",
    "Pick up point": "Highway Glory Restaurant",
    "Driver Details": "Driver-Sandeep",
    "M/F": "M",
    "Driver Address ": ""
  },
  {
    "Rout No": "",
    "Vendor": "",
    "Emp ID": "",
    "Name": "",
    "Contact No": "",
    "E mail ID": "",
    "Address": "",
    "Shift Time": "",
    "Pick up point": "",
    "Driver Details": "Mob-9021863195",
    "M/F": "",
    "Driver Address ": ""
  },
  {
    "Rout No": "Rout No",
    "Vendor": "Vendor",
    "Emp ID": "Emp ID",
    "Name": "Name",
    "Contact No": "Contact No",
    "E mail ID": "E mail ID",
    "Address": "Address",
    "Shift Time": "Shift Time",
    "Pick up point": "Pick up point",
    "Driver Details": "Driver Details",
    "M/F": "M/F",
    "Driver Address ": ""
  },
  {
    "Rout No": "P4",
    "Vendor": "FT",
    "Emp ID": "Escort",
    "Name": "Escort",
    "Contact No": "Escort",
    "E mail ID": "Escort",
    "Address": "Escort",
    "Shift Time": "Escort",
    "Pick up point": "Escort",
    "Driver Details": "MH49CW0218",
    "M/F": "M",
    "Driver Address ": "Add: NEAR KUNBI PURA BHAVAN HOUSE NO 435 AYACHIT MANDIR BUS STOP\n KUNBI PURA MAHAL Nagpur (Urban), Nagpur, MH"
  },
  {
    "Rout No": "P4",
    "Vendor": "FT",
    "Emp ID": "2574375",
    "Name": "Dipali Sharma",
    "Contact No": "9130920752",
    "E mail ID": "dipali.sharma@globallogic.com",
    "Address": "Lane-5, 315c Bharat Nagar behind Satya hotel, Kalmna Market Road Nagpur",
    "Shift Time": "05:00",
    "Pick up point": "Nirvana Residency, Kalamna Market Rd, Neta Ji Nagar, Pardi,",
    "Driver Details": "DRIVER- ANIKET",
    "M/F": "F",
    "Driver Address ": ""
  },
  {
    "Rout No": "P4",
    "Vendor": "FT",
    "Emp ID": "2572955",
    "Name": "Anushri Bhise",
    "Contact No": "9075483466",
    "E mail ID": "anushri.bhise@globallogic.com",
    "Address": "Plot No 33, Balaji Jewellers Lane, Ayodhya Nagar, Nagpur - 440024",
    "Shift Time": "05:00",
    "Pick up point": "Soham and Aluminium",
    "Driver Details": "MOB-9325911859",
    "M/F": "F",
    "Driver Address ": ""
  },
  {
    "Rout No": "P4",
    "Vendor": "FT",
    "Emp ID": "2563927",
    "Name": "Devalla Sudheer Kumar",
    "Contact No": "9963809283",
    "E mail ID": "devalla.kumar@globallogic.com",
    "Address": "Golden Vista Apartment,Flat No: 207, \n Besa, Nagpur:",
    "Shift Time": "05:00",
    "Pick up point": "St. Vincent Pallotti School",
    "Driver Details": "",
    "M/F": "M",
    "Driver Address ": ""
  },
  {
    "Rout No": "P4",
    "Vendor": "FT",
    "Emp ID": "2572249",
    "Name": "Minal Ninawe",
    "Contact No": "7887610598",
    "E mail ID": "minal.ninawe@globallogic.com",
    "Address": "Plot No 42, Near Puma showroom Manish Nagar, T-point Besa Road Nagpur- 440037",
    "Shift Time": "05:00",
    "Pick up point": "Puma showroom Manish Nagar",
    "Driver Details": "",
    "M/F": "F",
    "Driver Address ": ""
  },
  {
    "Rout No": "P4",
    "Vendor": "FT",
    "Emp ID": "2572827",
    "Name": "Siddheshwar Raghunath Raut",
    "Contact No": "9067067716",
    "E mail ID": "raut.raghunath@globallogic.com",
    "Address": "Flat no. 204, 2nd floor, Gruhalaxmi appartment 3, Maitree Nagar, Beltarodi, Nagpur",
    "Shift Time": "05:00",
    "Pick up point": "Maitree Nagar, Beltarodi",
    "Driver Details": "",
    "M/F": "M",
    "Driver Address ": ""
  },
  {
    "Rout No": "Rout No",
    "Vendor": "Vendor",
    "Emp ID": "Emp ID",
    "Name": "Name",
    "Contact No": "Contact No",
    "E mail ID": "E mail ID",
    "Address": "Address",
    "Shift Time": "Shift Time",
    "Pick up point": "Pick up point",
    "Driver Details": "Driver Details",
    "M/F": "M/F",
    "Driver Address ": ""
  },
  {
    "Rout No": "P5",
    "Vendor": "FT",
    "Emp ID": "2574323",
    "Name": "Abhay Marwade",
    "Contact No": "9175576069",
    "E mail ID": "abhay.marwade@globallogic.com",
    "Address": "PITRU CHHAYA NIWAS , QUARTER NUMBER 68/1 SOMWARI QUARTER,\n NEAR JUNA KAMGAR KALYAN KENDRA NAGPUR 440024",
    "Shift Time": "05:00",
    "Pick up point": "SOMWARI QUARTER",
    "Driver Details": "MH40DC0486",
    "M/F": "M",
    "Driver Address ": "Add P NO 190 MOTHI VIHIR MUMTAZ MANZIL SADABHAWANA NAGAR NAGPUR (URBAN), NAGPUR"
  },
  {
    "Rout No": "P5",
    "Vendor": "FT",
    "Emp ID": "2573885",
    "Name": "Kashmeni Sanjana",
    "Contact No": "7670995675",
    "E mail ID": "kashameni.sanjana@globallogic.com",
    "Address": "Behind Rahul Daily Needs , Beltarodi Road",
    "Shift Time": "05:00",
    "Pick up point": "Behind Rahul Daily Needs",
    "Driver Details": "DRIVER-SHAFIQUE",
    "M/F": "F",
    "Driver Address ": ""
  },
  {
    "Rout No": "P5",
    "Vendor": "FT",
    "Emp ID": "2574997",
    "Name": "Soma Lohitha",
    "Contact No": "6300844626",
    "E mail ID": "soma.lohitha@globallogic.com",
    "Address": "Behind Rahul Daily Needs , Beltarodi Road",
    "Shift Time": "05:00",
    "Pick up point": "Behind Rahul Daily Needs",
    "Driver Details": "MOB-9595420800",
    "M/F": "F",
    "Driver Address ": ""
  },
  {
    "Rout No": "P5",
    "Vendor": "FT",
    "Emp ID": "2573662",
    "Name": "Aparna Khadatkar",
    "Contact No": "7498457590",
    "E mail ID": "aparna.khadatkar@globallogic.com",
    "Address": "30/D, Ekta Housing Society\n Near Himalaya Empire, Opposite Ramteke Nagar\n Beltarodi Road",
    "Shift Time": "05:00",
    "Pick up point": "Behind Rahul Daily Needs",
    "Driver Details": "",
    "M/F": "F",
    "Driver Address ": ""
  },
  {
    "Rout No": "P5",
    "Vendor": "FT",
    "Emp ID": "2574857",
    "Name": "Pavani",
    "Contact No": "9059284958",
    "E mail ID": "",
    "Address": "waraj Palace, Shilpa Nagpur-440015. society, Manish Nagar,",
    "Shift Time": "05:00",
    "Pick up point": "Shilpa Nagpur society, Manish Nagar,",
    "Driver Details": "",
    "M/F": "F",
    "Driver Address ": ""
  },
  {
    "Rout No": "Rout No",
    "Vendor": "Vendor",
    "Emp ID": "Emp ID",
    "Name": "Name",
    "Contact No": "Contact No",
    "E mail ID": "E mail ID",
    "Address": "Address",
    "Shift Time": "Shift Time",
    "Pick up point": "Pick up point",
    "Driver Details": "Driver Details",
    "M/F": "M/F",
    "Driver Address ": ""
  },
  {
    "Rout No": "P6",
    "Vendor": "FT",
    "Emp ID": "2563946",
    "Name": "Anand Ram Kumar",
    "Contact No": "9494240460",
    "E mail ID": "pulavarthy.kumar@globallogic.com",
    "Address": "Plot no 95, Shrikrushna negar, manewada, bese road, Nagpur Landmar: Jagannath Mandir",
    "Shift Time": "07:00",
    "Pick up point": "Landmar: Jagannath Mandir",
    "Driver Details": "MH49CW0139",
    "M/F": "M",
    "Driver Address ": "61, Hudkeshwar Bujrug Hudkeshwar Bk. Nagpur Maharashtra 440034"
  },
  {
    "Rout No": "",
    "Vendor": "",
    "Emp ID": "",
    "Name": "",
    "Contact No": "",
    "E mail ID": "",
    "Address": "",
    "Shift Time": "",
    "Pick up point": "",
    "Driver Details": "Driver-Nikhil",
    "M/F": "Mob-9764325500",
    "Driver Address ": ""
  },
  {
    "Rout No": "Rout No",
    "Vendor": "Vendor",
    "Emp ID": "Emp ID",
    "Name": "Name",
    "Contact No": "Contact No",
    "E mail ID": "E mail ID",
    "Address": "Address",
    "Shift Time": "Shift Time",
    "Pick up point": "Pick up point",
    "Driver Details": "Driver Details",
    "M/F": "M/F",
    "Driver Address ": ""
  },
  {
    "Rout No": "P7",
    "Vendor": "FT",
    "Emp ID": "2576690",
    "Name": "Manjiri Dombale",
    "Contact No": "7888281289",
    "E mail ID": "",
    "Address": "65, Shri Sant Gajanan Nagar, New Narasala Road, \n Opposite Mauli Apartment, Nagpur - 440034",
    "Shift Time": "09:00",
    "Pick up point": "Mauli Apartment",
    "Driver Details": "MH49CW0078",
    "M/F": "F",
    "Driver Address ": "S/O Pradip Krushnarao Wasnik, near gajanan maharaj mandir, 220, new balaji nagar vistar,\n manewada road, bhgwan nagar, Nagpur, Maharashtra-440027"
  },
  {
    "Rout No": "P7",
    "Vendor": "FT",
    "Emp ID": "2577282",
    "Name": "Girivardhan",
    "Contact No": "9502542885",
    "E mail ID": "",
    "Address": "New Amarnagar, Near Manewada",
    "Shift Time": "09:00",
    "Pick up point": "New Amarnagar",
    "Driver Details": "DRIVER-SURAJ",
    "M/F": "M",
    "Driver Address ": ""
  },
  {
    "Rout No": "P7",
    "Vendor": "FT",
    "Emp ID": "NA",
    "Name": "sakshi",
    "Contact No": "8999187443",
    "E mail ID": "",
    "Address": "Subhangi Ghruh, Plot no 112, Besa-Manish Nagar Rd, besa, Nagpur, Besa Pipla, Maharashtra 440037",
    "Shift Time": "09:00",
    "Pick up point": "The I-school by edumeta besa",
    "Driver Details": "MOB-9561326459",
    "M/F": "F",
    "Driver Address ": ""
  },
  {
    "Rout No": "P7",
    "Vendor": "FT",
    "Emp ID": "NA",
    "Name": "Sagar",
    "Contact No": "6206701306",
    "E mail ID": "",
    "Address": "Samaj Bhushan Society, Somalwada,Wardha road, Nagpur.",
    "Shift Time": "09:00",
    "Pick up point": "Apollo Pharmacy",
    "Driver Details": "",
    "M/F": "M",
    "Driver Address ": ""
  },
  {
    "Rout No": "P7",
    "Vendor": "FT",
    "Emp ID": "NA",
    "Name": "Monika Jeswani",
    "Contact No": "7218617533",
    "E mail ID": "",
    "Address": "Cove Girls PG, Plot no 1, Shyam Sudha, Santaji society, Matakanya layout,\n Manish Nagar, Somalwada, Nagpur, Maharashtra, 440015",
    "Shift Time": "09:00",
    "Pick up point": "Gandhi automation Pvt Ltd gest house Manish nagar",
    "Driver Details": "",
    "M/F": "F",
    "Driver Address ": ""
  },
  {
    "Rout No": "P7",
    "Vendor": "FT",
    "Emp ID": "NA",
    "Name": "Tanuja",
    "Contact No": "8217018607",
    "E mail ID": "",
    "Address": "32, jaiprabhu society, Olive hotel inn, Manish Nagar, Shri Nagar, Nagpur",
    "Shift Time": "09:00",
    "Pick up point": "OYO Hotel Olive Stay Inn",
    "Driver Details": "",
    "M/F": "F",
    "Driver Address ": ""
  },
  {
    "Rout No": "Rout No",
    "Vendor": "Vendor",
    "Emp ID": "Emp ID",
    "Name": "Name",
    "Contact No": "Contact No",
    "E mail ID": "E mail ID",
    "Address": "Address",
    "Shift Time": "Shift Time",
    "Pick up point": "Pick up point",
    "Driver Details": "Driver Details",
    "M/F": "M/F",
    "Driver Address ": ""
  },
  {
    "Rout No": "P8",
    "Vendor": "FT",
    "Emp ID": "2577959",
    "Name": "Ayush Thakre",
    "Contact No": "7507841006",
    "E mail ID": "ayush.thakre@globallogic.com",
    "Address": "C04/204 Pioneer Regency Kt nagar Katol Road Nagpur 440013",
    "Shift Time": "09:00",
    "Pick up point": "Cafe Junglee Kt nagar",
    "Driver Details": "MH49CW1305",
    "M/F": "M",
    "Driver Address ": "P NO 15/B JAI GURUDEV NAGAR NEAR BHARAT GAS"
  },
  {
    "Rout No": "P8",
    "Vendor": "FT",
    "Emp ID": "NA",
    "Name": "Krunal Wath",
    "Contact No": "9356684307",
    "E mail ID": "krunal.wath@globallogic.com",
    "Address": "213, friends Colony katol Road Nagpur",
    "Shift Time": "09:00",
    "Pick up point": "friends Colony",
    "Driver Details": "Driver-Shantanu",
    "M/F": "M",
    "Driver Address ": "GODOWAUN MANEWADA BESA ROAD"
  },
  {
    "Rout No": "P8",
    "Vendor": "FT",
    "Emp ID": "2576808",
    "Name": "Sejal Shahare",
    "Contact No": "7517972498",
    "E mail ID": "sejal.shahare@globallogic.com",
    "Address": "D-201, Chimurkar Appartment, Chinchbhawan, wardha road, Nagpur, maharashtra",
    "Shift Time": "09:00",
    "Pick up point": "Zade child clinic Chinchbhawan",
    "Driver Details": "MOB-8261990745",
    "M/F": "F",
    "Driver Address ": "Nagpur (Urban), Nagpur"
  },
  {
    "Rout No": "",
    "Vendor": "",
    "Emp ID": "",
    "Name": "",
    "Contact No": "",
    "E mail ID": "",
    "Address": "",
    "Shift Time": "",
    "Pick up point": "",
    "Driver Details": "",
    "M/F": "",
    "Driver Address ": "PIN: 440027"
  },
  {
    "Rout No": "Rout No",
    "Vendor": "Vendor",
    "Emp ID": "Emp ID",
    "Name": "Name",
    "Contact No": "Contact No",
    "E mail ID": "E mail ID",
    "Address": "Address",
    "Shift Time": "Shift Time",
    "Pick up point": "Pick up point",
    "Driver Details": "Driver Details",
    "M/F": "M/F",
    "Driver Address ": ""
  },
  {
    "Rout No": "P9",
    "Vendor": "FT",
    "Emp ID": "2517958",
    "Name": "Shravan Meshram",
    "Contact No": "8888938203",
    "E mail ID": "shravan.meshram@globallogic.com",
    "Address": "H10,Rishikesh Town phase 2 ,near Grampanchayat school Bhilgaon Kamptee rd ,Nagpur 440029",
    "Shift Time": "09:00",
    "Pick up point": "Grampanchayat school Bhilgaon Kamptee",
    "Driver Details": "MH49CW0218",
    "M/F": "M",
    "Driver Address ": "NEAR KUNBI PURA BHAVAN HOUSE NO 435 AYACHIT MANDIR BUS STOP \nKUNBI PURA MAHAL Nagpur (Urban), Nagpur, MH"
  },
  {
    "Rout No": "P9",
    "Vendor": "FT",
    "Emp ID": "NA",
    "Name": "Pushpak Sakhare",
    "Contact No": "9545635896",
    "E mail ID": "",
    "Address": "Plot No. 78, 2nd floor, Arya Nagar near Sugat Nagar,Samta Nagar Road, \n Near Manmeete Bar and Lounge Restaurant",
    "Shift Time": "09:00",
    "Pick up point": "Sugat Nagar",
    "Driver Details": "DRIVER- ANIKET",
    "M/F": "M",
    "Driver Address ": ""
  },
  {
    "Rout No": "P9",
    "Vendor": "FT",
    "Emp ID": "2576887",
    "Name": "Likesh Barve",
    "Contact No": "9763879173",
    "E mail ID": "likesh.barve@globallogic.com",
    "Address": "Om sai nagar koradi road, plot no. 101 dhoke layout near sai mandir, Nagpur 440030",
    "Shift Time": "09:00",
    "Pick up point": "Om nagar koradi road",
    "Driver Details": "MOB-9325911859",
    "M/F": "M",
    "Driver Address ": ""
  },
  {
    "Rout No": "P9",
    "Vendor": "FT",
    "Emp ID": "2577311",
    "Name": "Geeta Rajput",
    "Contact No": "9545517502",
    "E mail ID": "geeta.rajput@globallogic.com",
    "Address": "#34 Amma pg Karve nagar Somalvada Wardha road Nagpur - 440025",
    "Shift Time": "09:00",
    "Pick up point": "Amma pg Karve nagar Somalvada",
    "Driver Details": "",
    "M/F": "F",
    "Driver Address ": ""
  },
  {
    "Rout No": "P9",
    "Vendor": "FT",
    "Emp ID": "NA",
    "Name": "Pranav Nachankar",
    "Contact No": "9623958699",
    "E mail ID": "",
    "Address": "Girikunj PG, chinch bhavan, Nagpur",
    "Shift Time": "09:00",
    "Pick up point": "Chinchbhuvan",
    "Driver Details": "",
    "M/F": "M",
    "Driver Address ": ""
  },
  {
    "Rout No": "Rout No",
    "Vendor": "Vendor",
    "Emp ID": "Emp ID",
    "Name": "Name",
    "Contact No": "Contact No",
    "E mail ID": "E mail ID",
    "Address": "Address",
    "Shift Time": "Shift Time",
    "Pick up point": "Pick up point",
    "Driver Details": "Driver Details",
    "M/F": "M/F",
    "Driver Address ": ""
  },
  {
    "Rout No": "P10",
    "Vendor": "FT",
    "Emp ID": "2576558",
    "Name": "Vansh Rewaskar",
    "Contact No": "9325990464",
    "E mail ID": "",
    "Address": "Elite homes pt no57, east samarth nagar, old, Wardha Rd, \n behind FCI Godown Road, Ajni, Nagpur, Maharashtra 440015",
    "Shift Time": "09:00",
    "Pick up point": "Ajni Electric Loco Shed",
    "Driver Details": "MH40CT4542",
    "M/F": "M",
    "Driver Address ": "House.No-285 Near Awachat Kirana Store Beldar Nagar, Narsala Hudkeshwar khurd. Nagpur (rural) Nagpur 440034"
  },
  {
    "Rout No": "P10",
    "Vendor": "FT",
    "Emp ID": "NA",
    "Name": "Mahesh Upadhyay",
    "Contact No": "7385021801",
    "E mail ID": "",
    "Address": "NARENDRA NAGAR",
    "Shift Time": "09:00",
    "Pick up point": "NARENDRA NAGAR",
    "Driver Details": "Driver-Tapan",
    "M/F": "M",
    "Driver Address ": ""
  },
  {
    "Rout No": "P10",
    "Vendor": "FT",
    "Emp ID": "NA",
    "Name": "Prachi jain",
    "Contact No": "8700451673",
    "E mail ID": "",
    "Address": "Plot no 45, Bhartiya Society, Prabhu nagar, New Manishnagar, Near Jayanti Mansion 9, Nagpur",
    "Shift Time": "09:00",
    "Pick up point": "New Manishnagar, Near Jayanti Mansion 9",
    "Driver Details": "Mob-8208223602",
    "M/F": "F",
    "Driver Address ": ""
  },
  {
    "Rout No": "Rout No",
    "Vendor": "Vendor",
    "Emp ID": "Emp ID",
    "Name": "Name",
    "Contact No": "Contact No",
    "E mail ID": "E mail ID",
    "Address": "Address",
    "Shift Time": "Shift Time",
    "Pick up point": "Pick up point",
    "Driver Details": "Driver Details",
    "M/F": "M/F",
    "Driver Address ": ""
  },
  {
    "Rout No": "P11",
    "Vendor": "FT",
    "Emp ID": "2577886",
    "Name": "Aryan Shende",
    "Contact No": "7057117995",
    "E mail ID": "aryan.shende@globallogic.com",
    "Address": "Santra Market, Kumbharpura Road, Near Rameshwari Dharmashala, Nagpur 440018",
    "Shift Time": "09:00",
    "Pick up point": "Santra Market",
    "Driver Details": "MH31FC8407",
    "M/F": "M",
    "Driver Address ": "PLOT NO-65, RATHI LAYOUT NR ASHIRWAD SCHOOL GODHANI ROAD \nZINGABAI TAKLI NAGPUR NAGPUR (M CORP.), NAGPUR,MH"
  },
  {
    "Rout No": "P11",
    "Vendor": "FT",
    "Emp ID": "2576584",
    "Name": "Deepak singh kushwah",
    "Contact No": "7249582964",
    "E mail ID": "",
    "Address": "D4, Kanchan Kiran housing, Ramdaspeth, Nagpur - 440012",
    "Shift Time": "09:00",
    "Pick up point": "Baidyashakti Lifecare Pvt. Ltd Ramdaspeth",
    "Driver Details": "Driver=Prashant",
    "M/F": "M",
    "Driver Address ": ""
  },
  {
    "Rout No": "P11",
    "Vendor": "FT",
    "Emp ID": "2574190",
    "Name": "Prashant Pathlavat",
    "Contact No": "9700451452",
    "E mail ID": "Prashanth.pathlavath@globallogic.com",
    "Address": "Sindhu residency 57 DRAP, Telecom Nagar, Nagpur",
    "Shift Time": "09:00",
    "Pick up point": "Telecom Nagar",
    "Driver Details": "Mob=7620971911",
    "M/F": "M",
    "Driver Address ": ""
  },
  {
    "Rout No": "P11",
    "Vendor": "FT",
    "Emp ID": "NA",
    "Name": "Ethel Delphine Collins",
    "Contact No": "9985802277",
    "E mail ID": "",
    "Address": "54, Utkarsh Building, near Sonegoan, Parate Nagar, Khamla, Nagpur, Maharashtra,",
    "Shift Time": "09:00",
    "Pick up point": "Parate Nagar, Khamla",
    "Driver Details": "",
    "M/F": "F",
    "Driver Address ": ""
  },
  {
    "Rout No": "Rout No",
    "Vendor": "Vendor",
    "Emp ID": "Emp ID",
    "Name": "Name",
    "Contact No": "Contact No",
    "E mail ID": "E mail ID",
    "Address": "Address",
    "Shift Time": "Shift Time",
    "Pick up point": "Pick up point",
    "Driver Details": "Driver Details",
    "M/F": "M/F",
    "Driver Address ": ""
  },
  {
    "Rout No": "P12",
    "Vendor": "FT",
    "Emp ID": "2563939",
    "Name": "Pulipati Krishna",
    "Contact No": "9440400155 /8341598148",
    "E mail ID": "pulipati.krishna@globallogic.com",
    "Address": "Near Drivven IT solutions LLP, near Shambhaji Square, \n Bandu Soni Layout, Subhash Nagar, Trimurthi Nagar,",
    "Shift Time": "09:00",
    "Pick up point": "Shubhash Nagar",
    "Driver Details": "MH49CW0876",
    "M/F": "M",
    "Driver Address ": "Dnyaneshwar Bus Stop, Kunbi pura Mahal, Nagpur City, PO: aneshwar Kalmegh, Plot No 441, Ayachit"
  },
  {
    "Rout No": "P12",
    "Vendor": "FT",
    "Emp ID": "",
    "Name": "Vishal Singh",
    "Contact No": "83569 58653",
    "E mail ID": "",
    "Address": "Hanswadwani apartment Flat 202 Plot no.1 Bhoge layout Near NIT Garden Trimurti nagar Nagpur 440022",
    "Shift Time": "09:00",
    "Pick up point": "Bhoge layout Near NIT Garden",
    "Driver Details": "Driver-Shreekant",
    "M/F": "F",
    "Driver Address ": ""
  },
  {
    "Rout No": "P12",
    "Vendor": "FT",
    "Emp ID": "NA",
    "Name": "Sayata Chakraborty",
    "Contact No": "9774766950",
    "E mail ID": "",
    "Address": "Chintaman Apartment, behind NIT Garden, Bhujbal Layout, Bhamti,Sainath Nagar, Trimurti Nagar, Nagpur, Maharashtra 440022",
    "Shift Time": "09:00",
    "Pick up point": "Creative Minds Art Academ NIT Garden",
    "Driver Details": "MOB-9326604708",
    "M/F": "F",
    "Driver Address ": ""
  },
  {
    "Rout No": "P12",
    "Vendor": "FT",
    "Emp ID": "2576584",
    "Name": "yash karambe",
    "Contact No": "9767612622",
    "E mail ID": "",
    "Address": "141 17b, Ram Mandir Road, Lokmanya Nagar, Nagpur, 17b,Ram Mandir Road, Lokmanya Nagar, Nagpur, NAGPUR,",
    "Shift Time": "09:00",
    "Pick up point": "NOTARY & ADV. SHILA GHAGRE Lokmanya Nagar",
    "Driver Details": "",
    "M/F": "M",
    "Driver Address ": ""
  },
  {
    "Rout No": "P12",
    "Vendor": "FT",
    "Emp ID": "2576692",
    "Name": "Azad Bhasme",
    "Contact No": "8530465461",
    "E mail ID": "",
    "Address": "Madhuban colony,Maharashtra chowk ,wanadongri,Hingna road,Nagpur- 441110",
    "Shift Time": "09:00",
    "Pick up point": "Madhuban colony, wanadongri",
    "Driver Details": "",
    "M/F": "M",
    "Driver Address ": ""
  },
  {
    "Rout No": "P12",
    "Vendor": "FT",
    "Emp ID": "2576563",
    "Name": "Shreya karale",
    "Contact No": "8767758699",
    "E mail ID": "",
    "Address": "hingna city society,hingna nagpur",
    "Shift Time": "09:00",
    "Pick up point": "Vedanshi Embroidery Hingna",
    "Driver Details": "",
    "M/F": "F",
    "Driver Address ": ""
  },
  {
    "Rout No": "Rout No",
    "Vendor": "Vendor",
    "Emp ID": "Emp ID",
    "Name": "Name",
    "Contact No": "Contact No",
    "E mail ID": "E mail ID",
    "Address": "Address",
    "Shift Time": "Shift Time",
    "Pick up point": "Pick up point",
    "Driver Details": "Driver Details",
    "M/F": "M/F",
    "Driver Address ": ""
  },
  {
    "Rout No": "P13",
    "Vendor": "FT",
    "Emp ID": "2563945",
    "Name": "Uday Tiwari",
    "Contact No": "9052594917",
    "E mail ID": "",
    "Address": "Besa - Manish Nagar",
    "Shift Time": "10:00",
    "Pick up point": "Besa - Manish Nagar",
    "Driver Details": "MH49CW0139",
    "M/F": "",
    "Driver Address ": " 61, Hudkeshwar Bujrug Hudkeshwar Bk. Nagpur Maharashtra 440034"
  },
  {
    "Rout No": "P13",
    "Vendor": "FT",
    "Emp ID": "NA",
    "Name": "Brej Kishore",
    "Contact No": "9096028331",
    "E mail ID": "NA",
    "Address": "Plot no 23, laxmi vihar, Near hotel royal centre point hotel heritage, behind airport center Nagpur",
    "Shift Time": "10:00",
    "Pick up point": "airport center hotel",
    "Driver Details": "Driver-Nikhil",
    "M/F": "",
    "Driver Address ": ""
  },
  {
    "Rout No": "",
    "Vendor": "",
    "Emp ID": "",
    "Name": "",
    "Contact No": "",
    "E mail ID": "",
    "Address": "",
    "Shift Time": "",
    "Pick up point": "",
    "Driver Details": "Mob-9764325500",
    "M/F": "",
    "Driver Address ": ""
  },
  {
    "Rout No": "Rout No",
    "Vendor": "Vendor",
    "Emp ID": "Emp ID",
    "Name": "Name",
    "Contact No": "Contact No",
    "E mail ID": "E mail ID",
    "Address": "Address",
    "Shift Time": "Shift Time",
    "Pick up point": "Pick up point",
    "Driver Details": "Driver Details",
    "M/F": "M/F",
    "Driver Address ": ""
  },
  {
    "Rout No": "P14",
    "Vendor": "FT",
    "Emp ID": "#######",
    "Name": "Pranay Wekhande",
    "Contact No": "8149299596 / 8208670107",
    "E mail ID": "pranay.wekhande@globallogic.com",
    "Address": "Plot No.11/A, 3rd Lane, Behind Saibaba Temple, Ayodhya Nagar,Mahavir Kirana Stores",
    "Shift Time": "13:00",
    "Pick up point": "Saibaba Temple, Ayodhya Nagar",
    "Driver Details": "MH49CW1305",
    "M/F": "M",
    "Driver Address ": "P NO 15/B JAI GURUDEV NAGAR NEAR BHARAT GAS"
  },
  {
    "Rout No": "P14",
    "Vendor": "FT",
    "Emp ID": "2574809",
    "Name": "Sayali Padole",
    "Contact No": "82372 63979",
    "E mail ID": "sayali.padole@globallogic.com",
    "Address": "Plot No 86, C/O Sanjay Chaudhari,Behind Kidzee \n Hudkeshwar,Shivangi Nagar, Hudkeshwar",
    "Shift Time": "13:00",
    "Pick up point": "Adarsh Lawn & Hall",
    "Driver Details": "Driver-Shantanu",
    "M/F": "F",
    "Driver Address ": "GODOWAUN MANEWADA BESA ROAD"
  },
  {
    "Rout No": "P14",
    "Vendor": "FT",
    "Emp ID": "NA",
    "Name": "Poorvi",
    "Contact No": "8458948881",
    "E mail ID": "poorvi.shrivas@globallogic.com",
    "Address": "32, jaiprabhu society, Olive hotel \n inn, Manish Nagar, Shri Nagar, Nagpur",
    "Shift Time": "13:00",
    "Pick up point": "OYO Hotel Olive Stay Inn",
    "Driver Details": "MOB-8261990745",
    "M/F": "F",
    "Driver Address ": "Nagpur (Urban), Nagpur"
  },
  {
    "Rout No": "",
    "Vendor": "",
    "Emp ID": "",
    "Name": "",
    "Contact No": "",
    "E mail ID": "",
    "Address": "",
    "Shift Time": "",
    "Pick up point": "",
    "Driver Details": "",
    "M/F": "",
    "Driver Address ": "PIN: 440027"
  },
  {
    "Rout No": "Rout No",
    "Vendor": "Vendor",
    "Emp ID": "Emp ID",
    "Name": "Name",
    "Contact No": "Contact No",
    "E mail ID": "E mail ID",
    "Address": "Address",
    "Shift Time": "Shift Time",
    "Pick up point": "Pick up point",
    "Driver Details": "Driver Details",
    "M/F": "M/F",
    "Driver Address ": ""
  },
  {
    "Rout No": "P15",
    "Vendor": "FT",
    "Emp ID": "NA",
    "Name": "Rushabh Bhagate",
    "Contact No": "9022023129",
    "E mail ID": "rushabh.bhagate@globallogic.com",
    "Address": "lot no. 115, Geeta, RPTS road, Surendra Nagar, Near Jerry Lawns,",
    "Shift Time": "13:00",
    "Pick up point": "Near Neeri School , Towards Ajni Sqr road",
    "Driver Details": "MH31FC8407",
    "M/F": "M",
    "Driver Address ": "PLOT NO-65, RATHI LAYOUT NR ASHIRWAD SCHOOL GODHANI ROAD\n ZINGABAI TAKLI NAGPUR NAGPUR (M CORP.), NAGPUR,MH"
  },
  {
    "Rout No": "P15",
    "Vendor": "FT",
    "Emp ID": "2573661",
    "Name": "Prabhat Priydarshi",
    "Contact No": "7903956186",
    "E mail ID": "prabhat.priydarshi@globallogic.com",
    "Address": "Near Sidhant Sakhsam Tower, Lokhande layout, Lokhande nagar, \n Parsodi, Subhash Nagar, Trimurti Nagar,Nagpur, Maharashtra - 440022",
    "Shift Time": "13:00",
    "Pick up point": "CCD IT park",
    "Driver Details": "Driver=Prashant",
    "M/F": "M",
    "Driver Address ": ""
  },
  {
    "Rout No": "P15",
    "Vendor": "FT",
    "Emp ID": "2560101",
    "Name": "Vajja Bhanu Prakash",
    "Contact No": "9381031939",
    "E mail ID": "vajja.prakash@globallogic.com",
    "Address": "Near Drivven IT solutions LLP,near shambhaji square,Bandu soni layout,\n subhash nagar,trimurthi nagar,nagpur,maharashtra 440022",
    "Shift Time": "13:00",
    "Pick up point": "Shubhash Nagar",
    "Driver Details": "Mob=7620971911",
    "M/F": "",
    "Driver Address ": ""
  },
  {
    "Rout No": "P15",
    "Vendor": "FT",
    "Emp ID": "2572172",
    "Name": "Nikhil Ambule",
    "Contact No": "7218518122",
    "E mail ID": "nikhil.ambule@globallogic.com",
    "Address": "Sadguru kirana and general store,Sai nagar near puliya, 1, Jaitala Rd, near dattey layout,\n Wadeskar Layout, Jaitala, string:Nagpur, Nagpur, Maharashtra 440036",
    "Shift Time": "13:00",
    "Pick up point": "Sheshrao Kohale Vidhyalaya & jr college",
    "Driver Details": "",
    "M/F": "M",
    "Driver Address ": ""
  },
  {
    "Rout No": "Rout No",
    "Vendor": "Vendor",
    "Emp ID": "Emp ID",
    "Name": "Name",
    "Contact No": "Contact No",
    "E mail ID": "E mail ID",
    "Address": "Address",
    "Shift Time": "Shift Time",
    "Pick up point": "Pick up point",
    "Driver Details": "Driver Details",
    "M/F": "M/F",
    "Driver Address ": ""
  },
  {
    "Rout No": "P16",
    "Vendor": "FT",
    "Emp ID": "2573846",
    "Name": "Yash Dubey",
    "Contact No": "8815498610",
    "E mail ID": "yash.dubey@globallogic.com",
    "Address": "Jaywant co operative housing society, behind Ramteke nagar, \n Omkar Nagar, Nagpur, Maharashtra 440027",
    "Shift Time": "13:00",
    "Pick up point": "Roshan Mini Transport",
    "Driver Details": "MH49CW0876",
    "M/F": "M",
    "Driver Address ": "Dnyaneshwar Bus Stop, Kunbi pura Mahal, Nagpur City, PO: aneshwar Kalmegh, Plot No 441, Ayachit"
  },
  {
    "Rout No": "P16",
    "Vendor": "FT",
    "Emp ID": "2564448",
    "Name": "Kumar Adarsh",
    "Contact No": "7903567319",
    "E mail ID": "",
    "Address": "52 Jai Durga Society, Narendra Nagar, Nagpur pin -440015,",
    "Shift Time": "13:00",
    "Pick up point": "Neelkamal Homes",
    "Driver Details": "Driver-Shreekant",
    "M/F": "M",
    "Driver Address ": ""
  },
  {
    "Rout No": "P16",
    "Vendor": "FT",
    "Emp ID": "2575523",
    "Name": "Abhijit Zade",
    "Contact No": "9730462485",
    "E mail ID": "",
    "Address": "Radhakrishna Apartment Behind Krishna Super Mart 2 Manish Nagar, Nagpur",
    "Shift Time": "13:00",
    "Pick up point": "Krishna Super Mart 2",
    "Driver Details": "MOB-9326604708",
    "M/F": "M",
    "Driver Address ": ""
  },
  {
    "Rout No": "P16",
    "Vendor": "FT",
    "Emp ID": "2573568",
    "Name": "Nisha Shyamsukha",
    "Contact No": "9093931909",
    "E mail ID": "nisha.shyamsukha@globallogic.com",
    "Address": "Harihar Gokul Park 2, near Axis Bank, Manish Nagar,",
    "Shift Time": "13:00",
    "Pick up point": "Axis Bank, Manish Nagar",
    "Driver Details": "",
    "M/F": "F",
    "Driver Address ": ""
  },
  {
    "Rout No": "P16",
    "Vendor": "FT",
    "Emp ID": "2572738",
    "Name": "Kartik Ukhalkar",
    "Contact No": "7588787601",
    "E mail ID": "kartik.ukhalkar@globallogic.com",
    "Address": "Ground floor, Orchid landmark, Behind Manomay Homes hotel, New Manish Naga",
    "Shift Time": "13:00",
    "Pick up point": "Hotel Manomay",
    "Driver Details": "",
    "M/F": "M",
    "Driver Address ": ""
  },
  {
    "Rout No": "P16",
    "Vendor": "FT",
    "Emp ID": "2564924",
    "Name": "Pranay Haste",
    "Contact No": "9860582460",
    "E mail ID": "pranay.haste@globallogic.com",
    "Address": "SPDL Aashray Apartment, Beltarodi, Besa Pipla, Nagpur.",
    "Shift Time": "13:00",
    "Pick up point": "REVOLVE FITNESS GYM",
    "Driver Details": "",
    "M/F": "M",
    "Driver Address ": ""
  },
  {
    "Rout No": "Rout No",
    "Vendor": "Vendor",
    "Emp ID": "Emp ID",
    "Name": "Name",
    "Contact No": "Contact No",
    "E mail ID": "E mail ID",
    "Address": "Address",
    "Shift Time": "Shift Time",
    "Pick up point": "Pick up point",
    "Driver Details": "Driver Details",
    "M/F": "M/F",
    "Driver Address ": ""
  },
  {
    "Rout No": "P17",
    "Vendor": "FT",
    "Emp ID": "2573901",
    "Name": "Atharva Deo",
    "Contact No": "9881103408",
    "E mail ID": "atharva.deo@globallogic.com",
    "Address": "P.N. 678, Deshpande layout, Bhandara road, \n Wardhaman Nagar, Near Haldiram's building, Nagpur-440008",
    "Shift Time": "13:00",
    "Pick up point": "day 2 day",
    "Driver Details": "MH49CW0078",
    "M/F": "M",
    "Driver Address ": "S/O Pradip Krushnarao Wasnik, near gajanan maharaj mandir, 220, new balaji nagar vistar, \nmanewada road, bhgwan nagar, Nagpur, Maharashtra-440027"
  },
  {
    "Rout No": "P17",
    "Vendor": "FT",
    "Emp ID": "2572338",
    "Name": "Ravindra Farkade",
    "Contact No": "7888182312",
    "E mail ID": "ravindra.farkade@globallogic.com",
    "Address": "Rajat Gawre House, Gurukunj Nagar, Near Vigyan nagar, \n Manewada Nagpur,440034",
    "Shift Time": "13:00",
    "Pick up point": "Front of Rajesh Saoji Bhojnalaya",
    "Driver Details": "DRIVER-SURAJ",
    "M/F": "M",
    "Driver Address ": ""
  },
  {
    "Rout No": "P17",
    "Vendor": "FT",
    "Emp ID": "2532274",
    "Name": "Lavakumar Khanapur",
    "Contact No": "6363087687",
    "E mail ID": "lavakumar.khanapur@globallogic.com",
    "Address": "shilpa society,uco Bank behind somalwada branch manish Nagar",
    "Shift Time": "13:00",
    "Pick up point": "Green Relocation",
    "Driver Details": "MOB-9561326459",
    "M/F": "M",
    "Driver Address ": ""
  },
  {
    "Rout No": "P17",
    "Vendor": "FT",
    "Emp ID": "NA",
    "Name": "Shubhankar Das",
    "Contact No": "7001818737",
    "E mail ID": "",
    "Address": "Plot no 57,Shilpa co.op.society, Narendra Nagar.nagpur 440015",
    "Shift Time": "13:00",
    "Pick up point": "Green Relocation",
    "Driver Details": "",
    "M/F": "M",
    "Driver Address ": ""
  },
  {
    "Rout No": "P17",
    "Vendor": "FT",
    "Emp ID": "2573848",
    "Name": "Meghana B U",
    "Contact No": "7899130650",
    "E mail ID": "meghana.u@globallogic.com",
    "Address": "#34 Amma pg Karve nagar Somalvada Wardha road Nagpur - 440025",
    "Shift Time": "13:00",
    "Pick up point": "Kanak Car center",
    "Driver Details": "",
    "M/F": "F",
    "Driver Address ": ""
  }
]